databricks/__init__.py
databricks/bundles/__init__.py
databricks/bundles/build.py
databricks/bundles/py.typed
databricks/bundles/resource.py
databricks/bundles/variables.py
databricks/bundles/compute/__init__.py
databricks/bundles/compute/models/__init__.py
databricks/bundles/compute/models/adlsgen2_info.py
databricks/bundles/compute/models/auto_scale.py
databricks/bundles/compute/models/aws_attributes.py
databricks/bundles/compute/models/aws_availability.py
databricks/bundles/compute/models/azure_attributes.py
databricks/bundles/compute/models/azure_availability.py
databricks/bundles/compute/models/clients_types.py
databricks/bundles/compute/models/clone_cluster.py
databricks/bundles/compute/models/cluster_log_conf.py
databricks/bundles/compute/models/cluster_source.py
databricks/bundles/compute/models/cluster_spec.py
databricks/bundles/compute/models/compute_spec.py
databricks/bundles/compute/models/data_security_mode.py
databricks/bundles/compute/models/dbfs_storage_info.py
databricks/bundles/compute/models/docker_basic_auth.py
databricks/bundles/compute/models/docker_image.py
databricks/bundles/compute/models/ebs_volume_type.py
databricks/bundles/compute/models/environment.py
databricks/bundles/compute/models/gcp_attributes.py
databricks/bundles/compute/models/gcp_availability.py
databricks/bundles/compute/models/gcs_storage_info.py
databricks/bundles/compute/models/init_script_info.py
databricks/bundles/compute/models/library.py
databricks/bundles/compute/models/local_file_info.py
databricks/bundles/compute/models/log_analytics_info.py
databricks/bundles/compute/models/runtime_engine.py
databricks/bundles/compute/models/s3_storage_info.py
databricks/bundles/compute/models/volumes_storage_info.py
databricks/bundles/compute/models/workload_type.py
databricks/bundles/compute/models/workspace_storage_info.py
databricks/bundles/internal/_diagnostics.py
databricks/bundles/internal/_loader.py
databricks/bundles/internal/_transform.py
databricks_pydabs-0.6.0.dist-info/LICENSE
databricks_pydabs-0.6.0.dist-info/METADATA
databricks_pydabs-0.6.0.dist-info/WHEEL
databricks_pydabs-0.6.0.dist-info/entry_points.txt
databricks_pydabs-0.6.0.dist-info/top_level.txt
databricks_pydabs-0.6.0.dist-info/RECORD
