Metadata-Version: 2.1
Name: databricks-pydabs
Version: 0.6.0
Author-email: Gleb Kanterov <gleb.kanterov@databricks.com>
License: DB license
Requires-Python: >=3.10
License-File: LICENSE
Provides-Extra: dev
Requires-Dist: pytest; extra == "dev"
Requires-Dist: pytest-cov; extra == "dev"
Requires-Dist: ruff==0.2.1; extra == "dev"
Requires-Dist: typing-extensions==4.12.2; extra == "dev"
